numworkshop.py
numworkshop-0.1.4.dist-info/license
numworkshop-0.1.4.dist-info/WHEEL
numworkshop-0.1.4.dist-info/METADATA
numworkshop-0.1.4.dist-info/RECORD
