Metadata-Version: 2.1
Name: numworkshop
Version: 0.1.4
Summary: A python wrapper for the Numworks workshop
Home-page: https://workshop.numworks.com/
License: MIT
Keywords: Numworks,workshop
Author: Evann DREUMONT
Author-email: 53308142+LeGmask@users.noreply.github.com
Requires-Python: >=3.8,<4.0
Classifier: Development Status :: 4 - Beta
Classifier: License :: OSI Approved :: MIT License
Classifier: Programming Language :: Python :: 3
Classifier: Programming Language :: Python :: 3.8
Classifier: Topic :: Internet
Classifier: Topic :: Utilities
Requires-Dist: beautifulsoup4 (>=4.9.3,<5.0.0)
Requires-Dist: requests (>=2.25.1,<3.0.0)
Project-URL: Repository, https://github.com/LeGmask/numWorkshop
